setup.cfg
setup.py
taz/__init__.py
taz/game.py
tazlib.egg-info/PKG-INFO
tazlib.egg-info/SOURCES.txt
tazlib.egg-info/dependency_links.txt
tazlib.egg-info/top_level.txt