Metadata-Version: 1.1
Name: tazlib
Version: 1.3.1
Summary: Taz - Game Loop and Scene Stack Manager
Home-page: https://github.com/mkli90/Taz
Author: Max Klingmann <KlingmannM@gmail.com>
Author-email: KlingmannM@gmail.com
License: GPLv3
Download-URL: https://github.com/mkli90/Taz/tarball/1.3.1
Platform: UNKNOWN
Classifier: Intended Audience :: Developers
Classifier: Development Status :: 5 - Production/Stable
Classifier: License :: OSI Approved :: GNU General Public License v3 (GPLv3)
Classifier: Natural Language :: English
Classifier: Programming Language :: Python :: 2.7
Classifier: Programming Language :: Python :: 3.4
Classifier: Topic :: Games/Entertainment
Classifier: Topic :: Software Development :: Libraries
